smarttest/__init__.py
smarttest/app.py
smarttest/auto_import.py
smarttest/cli.py
smarttest/launcher.py
smarttest/reporter.py
smarttest/terminal_interface.py
smarttest/tester.py
smarttest/web_interface.py
smarttest-1.0.1.dist-info/licenses/LICENSE
smarttest-1.0.1.dist-info/METADATA
smarttest-1.0.1.dist-info/WHEEL
smarttest-1.0.1.dist-info/entry_points.txt
smarttest-1.0.1.dist-info/top_level.txt
smarttest-1.0.1.dist-info/RECORD
