Metadata-Version: 2.4
Name: smarttest
Version: 1.0.1
Summary: Intelligent Python code testing library with real-time error detection
Home-page: https://github.com/smarttest/smarttest
Author: SmartTest Team
Author-email: SmartTest Team <team@smarttest.dev>
Maintainer: SmartTest Team
Maintainer-email: SmartTest Team <team@smarttest.dev>
License: MIT
Project-URL: Homepage, https://github.com/smarttest/smarttest
Project-URL: Documentation, https://smarttest.readthedocs.io/
Project-URL: Repository, https://github.com/smarttest/smarttest.git
Project-URL: Bug Tracker, https://github.com/smarttest/smarttest/issues
Project-URL: Source Code, https://github.com/smarttest/smarttest
Keywords: python,testing,code-quality,error-detection,real-time,monitoring,development,tools,linter,static-analysis
Platform: any
Classifier: Development Status :: 5 - Production/Stable
Classifier: Intended Audience :: Developers
Classifier: Topic :: Software Development :: Testing
Classifier: Topic :: Software Development :: Quality Assurance
Classifier: Topic :: Software Development :: Libraries :: Python Modules
Classifier: License :: OSI Approved :: MIT License
Classifier: Programming Language :: Python :: 3
Classifier: Programming Language :: Python :: 3.7
Classifier: Programming Language :: Python :: 3.8
Classifier: Programming Language :: Python :: 3.9
Classifier: Programming Language :: Python :: 3.10
Classifier: Programming Language :: Python :: 3.11
Classifier: Programming Language :: Python :: 3.12
Classifier: Operating System :: OS Independent
Classifier: Environment :: Console
Classifier: Environment :: X11 Applications
Classifier: Environment :: Win32 (MS Windows)
Classifier: Environment :: MacOS X
Requires-Python: >=3.7
License-File: LICENSE
Requires-Dist: colorama>=0.4.4
Provides-Extra: dev
Requires-Dist: pytest>=6.0; extra == "dev"
Requires-Dist: pytest-cov>=2.0; extra == "dev"
Requires-Dist: black>=21.0; extra == "dev"
Requires-Dist: flake8>=3.8; extra == "dev"
Requires-Dist: mypy>=0.800; extra == "dev"
Provides-Extra: docs
Requires-Dist: sphinx>=4.0; extra == "docs"
Requires-Dist: sphinx-rtd-theme>=0.5; extra == "docs"
Requires-Dist: myst-parser>=0.15; extra == "docs"
Dynamic: author
Dynamic: home-page
Dynamic: license-file
Dynamic: maintainer
Dynamic: platform
Dynamic: requires-python
